ai_model_match/__init__.py
ai_model_match/aimm_base_client.py
ai_model_match/aimm_client.py
ai_model_match/aimm_exceptions.py
ai_model_match/dto/__init__.py
ai_model_match/dto/aimm_feedback_dto.py
ai_model_match/dto/aimm_picker_dto.py
ai_model_match-1.0.4.dist-info/licenses/LICENSE
ai_model_match-1.0.4.dist-info/METADATA
ai_model_match-1.0.4.dist-info/WHEEL
ai_model_match-1.0.4.dist-info/top_level.txt
ai_model_match-1.0.4.dist-info/RECORD
