Metadata-Version: 2.4
Name: ai-model-match
Version: 1.0.4
Summary: AI Model Match is an open-source service that helps product teams release, test, and optimize prompt configurations for AI-powered applications.
Author-email: Lorenzo Castelli <lory.castelli+modelmatch@gmail.com>
License-Expression: MIT
Project-URL: Homepage, https://pypi.org/project/ai-model-match
Project-URL: Repository, https://github.com/ai-model-match/sdk-python
Classifier: Programming Language :: Python :: 3
Classifier: Operating System :: OS Independent
Requires-Python: >=3.8
License-File: LICENSE
Dynamic: license-file
